README.md
setup.py
pynot/__init__.py
pynot/admin.py
pynot/apps.py
pynot/factories.py
pynot/models.py
pynot/permissions.py
pynot/serializers.py
pynot/tasks.py
pynot/tests.py
pynot/urls.py
pynot/views.py
pynot.egg-info/PKG-INFO
pynot.egg-info/SOURCES.txt
pynot.egg-info/dependency_links.txt
pynot.egg-info/requires.txt
pynot.egg-info/top_level.txt
pynot/migrations/0001_initial.py
pynot/migrations/__init__.py
pynot/utils/__init__.py
pynot/utils/util_email.py