Metadata-Version: 2.1
Name: pynot
Version: 1.1.1
Summary: Django library to manage notifications emitted by an application
Home-page: https://github.com/intelligenia/pynot
Author: José Carlos Calvo Tudela
Author-email: jcctudela@gmail.com
License: Apache 2.0
Keywords: emails,notifications,notification manager,REST notification config
Platform: UNKNOWN
Classifier: Development Status :: 5 - Production/Stable
Classifier: Framework :: Django
Requires-Python: >=3.5.0
